ckanext/__init__.py
ckanext/tour/__init__.py
ckanext/tour/collection.py
ckanext/tour/config.py
ckanext/tour/exception.py
ckanext/tour/helpers.py
ckanext/tour/model.py
ckanext/tour/plugin.py
ckanext/tour/assets/webassets.yml
ckanext/tour/assets/css/style.css
ckanext/tour/assets/css/vendor/shepherd.min.css
ckanext/tour/assets/js/tour-image-upload.js
ckanext/tour/assets/js/tour-init.js
ckanext/tour/assets/js/tour-steps.js
ckanext/tour/assets/js/vendor/bodyScrollLock.min.js
ckanext/tour/assets/js/vendor/floating-ui.core.umd.js
ckanext/tour/assets/js/vendor/mobile-detect.min.js
ckanext/tour/assets/js/vendor/shepherd.min.js
ckanext/tour/assets/js/vendor/draggable/plugins.min.js
ckanext/tour/assets/js/vendor/draggable/sort-animation.min.js
ckanext/tour/assets/js/vendor/draggable/sortable.min.js
ckanext/tour/logic/action.py
ckanext/tour/logic/auth.py
ckanext/tour/logic/schema.py
ckanext/tour/logic/validators.py
ckanext/tour/migration/tour/alembic.ini
ckanext/tour/migration/tour/env.py
ckanext/tour/migration/tour/script.py.mako
ckanext/tour/migration/tour/versions/c9e5d4235e58_create_tour_tourstep_tourstepimage_.py
ckanext/tour/templates/base.html
ckanext/tour/templates/tour/record.html
ckanext/tour/templates/tour/tour_404.html
ckanext/tour/templates/tour/tour_add.html
ckanext/tour/templates/tour/tour_delete.html
ckanext/tour/templates/tour/tour_edit.html
ckanext/tour/templates/tour/tour_list.html
ckanext/tour/templates/tour/snippets/tour_form.html
ckanext/tour/templates/tour/snippets/tour_image_upload.html
ckanext/tour/templates/tour/snippets/tour_step.html
ckanext/tour/tests/conftest.py
ckanext/tour/tests/factories.py
ckanext/tour/tests/helpers.py
ckanext/tour/tests/logic/__init__.py
ckanext/tour/tests/logic/test_action.py
ckanext/tour/tests/logic/test_auth.py
ckanext/tour/views/__init__.py
ckanext/tour/views/tour_add.py
ckanext/tour/views/tour_config.py
ckanext/tour/views/tour_delete.py
ckanext/tour/views/tour_list.py
ckanext/tour/views/tour_update.py
ckanext_tour-0.3.0.dist-info/LICENSE
ckanext_tour-0.3.0.dist-info/METADATA
ckanext_tour-0.3.0.dist-info/WHEEL
ckanext_tour-0.3.0.dist-info/entry_points.txt
ckanext_tour-0.3.0.dist-info/top_level.txt
ckanext_tour-0.3.0.dist-info/RECORD
